Metadata-Version: 2.4
Name: amazon-scrapper-pipeline
Version: 0.2.6
Summary: Independent URL and Product scraping pipelines for Amazon
Author-email: Dhruv Saxena <dhruvsaxena@dhruvsaxena25.com>
License: MIT
Project-URL: Repository, https://github.com/dhruvsaxena25/amazon-scrapper-pipeline
Project-URL: Issues, https://github.com/dhruvsaxena25/amazon-scrapper-pipeline/issues
Keywords: amazon,scraper,web-scraping,selenium,pipeline
Classifier: Development Status :: 3 - Alpha
Classifier: Intended Audience :: Developers
Classifier: License :: OSI Approved :: MIT License
Classifier: Programming Language :: Python :: 3
Classifier: Programming Language :: Python :: 3.10
Classifier: Programming Language :: Python :: 3.11
Classifier: Programming Language :: Python :: 3.12
Classifier: Operating System :: OS Independent
Requires-Python: >=3.10
License-File: LICENSE
Requires-Dist: selenium>=4.0.0
Requires-Dist: pyyaml>=6.0
Requires-Dist: beautifulsoup4>=4.9.0
Requires-Dist: requests>=2.25.0
Requires-Dist: webdriver-manager>=3.8.0
Requires-Dist: undetected-chromedriver>=3.5.0
Requires-Dist: pandas>=1.3.0
Requires-Dist: python-dateutil>=2.8.0
Requires-Dist: setuptools>=65.5.0
Requires-Dist: structlog>=23.1.0
Requires-Dist: lxml>=4.9.0
Requires-Dist: fastapi[standard]>=0.115.0
Requires-Dist: uvicorn[standard]>=0.30.0
Requires-Dist: jinja2==3.1.6
Requires-Dist: aiofiles==25.1.0
Dynamic: license-file
